LICENSE
quasarpy/__init__.py
quasarpy/__main__.py
quasarpy/_version.py
quasarpy/algorithm/__init__.py
quasarpy/algorithm/detector.py
quasarpy/algorithm/llm.py
quasarpy/algorithm/model/class_model.json
quasarpy/algorithm/model/method_model.json
quasarpy/cli/__init__.py
quasarpy/handler/__init__.py
quasarpy/handler/issue.py
quasarpy/tests/__init__.py
quasarpy/tests/conftest.py
quasarpy/tests/test_algorithm.py
quasarpy/tests/test_cli.py
quasarpy/tests/test_handler.py
quasarpy/tests/test_utils.py
quasarpy/utils/__init__.py
quasarpy/utils/analyser.py
quasarpy/utils/ascii.py
quasarpy/utils/errors.py
quasarpy/utils/logger.py
quasarpy/utils/prompt_template.py
quasarpy/utils/redis_server.py
quasarpy/utils/templates/report_template.html
quasarpy-0.2.2.dist-info/LICENSE
quasarpy-0.2.2.dist-info/METADATA
quasarpy-0.2.2.dist-info/WHEEL
quasarpy-0.2.2.dist-info/entry_points.txt
quasarpy-0.2.2.dist-info/RECORD
